get_contribution/__init__.py
get_contribution/main.py
get_contribution/utilities.py
get_contribution-1.0.0.dist-info/METADATA
get_contribution-1.0.0.dist-info/WHEEL
get_contribution-1.0.0.dist-info/entry_points.txt
get_contribution-1.0.0.dist-info/RECORD
