Metadata-Version: 2.1
Name: get-contribution
Version: 1.0.0
Summary: Get your contribution in a Git Repo.
Author: Hieu Vuong
Author-email: hieuvuong.cs@gmail.com
Requires-Python: >=3.10,<4.0
Classifier: Programming Language :: Python :: 3
Classifier: Programming Language :: Python :: 3.10
Classifier: Programming Language :: Python :: 3.11
Requires-Dist: typer[all] (>=0.7.0,<0.8.0)
